foliant/preprocessors/history.py
foliantcontrib_history-1.0.10.dist-info/licenses/LICENSE
foliantcontrib_history-1.0.10.dist-info/METADATA
foliantcontrib_history-1.0.10.dist-info/WHEEL
foliantcontrib_history-1.0.10.dist-info/top_level.txt
foliantcontrib_history-1.0.10.dist-info/RECORD
